agent_planck-0.1.2.dist-info/licenses/LICENSE
agentplanck/__init__.py
agentplanck/agent/__init__.py
agentplanck/agent/examples.py
agentplanck/agent/prompts.py
agentplanck/agent/service.py
agentplanck/agent/views.py
agentplanck/agent/message_manager/__init__.py
agentplanck/agent/message_manager/service.py
agentplanck/agent/message_manager/views.py
agentplanck/mcp_client/__init__.py
agentplanck/mcp_client/examples.py
agentplanck/mcp_client/service.py
agentplanck/tools/__init__.py
agentplanck/tools/examples.py
agentplanck/tools/service.py
agentplanck/tools/views.py
agentplanck/tools/registery/service.py
agentplanck/tools/registery/views.py
agentplanck/utils/general.py
agent_planck-0.1.2.dist-info/METADATA
agent_planck-0.1.2.dist-info/WHEEL
agent_planck-0.1.2.dist-info/top_level.txt
agent_planck-0.1.2.dist-info/RECORD
