Metadata-Version: 2.4
Name: agent-planck
Version: 0.1.2
Summary: A lightweight production ready agentic framework to build your agents
Author-email: Afreedi z <afreedisulfiker@gmail.com>
License: MIT
Keywords: agent,agentic framework,artifical intelligence,langchain
Classifier: Programming Language :: Python :: 3
Classifier: License :: OSI Approved :: MIT License
Requires-Python: >=3.8
License-File: LICENSE
Requires-Dist: requests>=2.0
Dynamic: license-file
